LICENSE.txt
MANIFEST.in
README.md
setup.cfg
setup.py
SNPknock/__init__.py
SNPknock/fastphase.py
SNPknock/knockoffs.cpp
SNPknock/knockoffs.pyx
SNPknock/models.py
SNPknock.egg-info/PKG-INFO
SNPknock.egg-info/SOURCES.txt
SNPknock.egg-info/dependency_links.txt
SNPknock.egg-info/requires.txt
SNPknock.egg-info/top_level.txt
SNPknock/knockoffs/__init__.py
SNPknock/knockoffs/dmc.cpp
SNPknock/knockoffs/dmc.h
SNPknock/knockoffs/dmc.pyx
SNPknock/knockoffs/genotypes.cpp
SNPknock/knockoffs/genotypes.h
SNPknock/knockoffs/genotypes.pyx
SNPknock/knockoffs/haplotypes.cpp
SNPknock/knockoffs/haplotypes.h
SNPknock/knockoffs/haplotypes.pyx
SNPknock/knockoffs/hmm.cpp
SNPknock/knockoffs/hmm.h
SNPknock/knockoffs/hmm.pyx
SNPknock/knockoffs/knockoffs.cpp
SNPknock/knockoffs/knockoffs.h
SNPknock/knockoffs/utils.cpp
SNPknock/knockoffs/utils.h
SNPknock/tests/test_knockoffs.py