Metadata-Version: 1.2
Name: SNPknock
Version: 0.8.2
Summary: Generates knockoff copies of HMMs and genomic data.
Home-page: http://web.stanford.edu/~msesia/snpknock/
Author: Matteo Sesia
Author-email: msesia@stanford.edu
Maintainer: Matteo Sesia
Maintainer-email: msesia@stanford.edu
License: GPL-v3 license
Download-URL: http://web.stanford.edu/~msesia/snpknock/install.html
Platform: OS Independent
Classifier: Development Status :: 4 - Beta
Classifier: Environment :: Console
Classifier: Intended Audience :: Science/Research
Classifier: License :: OSI Approved :: GNU General Public License v3 or later (GPLv3+)
Classifier: Operating System :: OS Independent
Classifier: Programming Language :: Python
Classifier: Topic :: Scientific/Engineering
Requires: numpy (>=1.13.1)
Requires: Cython (>=0.26)
Provides: SNPknock
